tests/__init__.py
tests/test_twopiece.py
twopiece/__init__.py
twopiece/double.py
twopiece/scale.py
twopiece/shape.py
twopiece/sinharcsinh.py
twopiece/utils.py
twopiece-1.3.1.dist-info/LICENSE
twopiece-1.3.1.dist-info/METADATA
twopiece-1.3.1.dist-info/WHEEL
twopiece-1.3.1.dist-info/top_level.txt
twopiece-1.3.1.dist-info/RECORD
