Metadata-Version: 2.1
Name: twopiece
Version: 1.3.1
Summary: Two-Piece Distributions Implementation
Home-page: https://github.com/quantgirluk/twopiece
Author: Dialid Santiago 
Author-email: d.santiago@outlook.com
Classifier: Programming Language :: Python :: 3
Classifier: License :: OSI Approved :: MIT License
Classifier: Operating System :: OS Independent
Requires-Python: >=3.6
License-File: LICENSE
Requires-Dist: numpy (>=1.13.1)
Requires-Dist: scipy (>=0.19.1)
Requires-Dist: matplotlib (>=2.2.2)
Requires-Dist: seaborn (>=0.8)
